toolslm/__init__.py
toolslm/_modidx.py
toolslm/download.py
toolslm/funccall.py
toolslm/inspecttools.py
toolslm/md_hier.py
toolslm/shell.py
toolslm/xml.py
toolslm-0.3.26.dist-info/licenses/LICENSE
toolslm-0.3.26.dist-info/METADATA
toolslm-0.3.26.dist-info/WHEEL
toolslm-0.3.26.dist-info/entry_points.txt
toolslm-0.3.26.dist-info/top_level.txt
toolslm-0.3.26.dist-info/RECORD
